jupyxml/__init__.py
jupyxml/accordian_creator.py
jupyxml/skeleton.py
jupyxml/visualiser.py
jupyxml/styles/__init__.py
jupyxml/styles/jupyxml.css
jupyxml-0.2.3.dist-info/AUTHORS.rst
jupyxml-0.2.3.dist-info/LICENSE.txt
jupyxml-0.2.3.dist-info/METADATA
jupyxml-0.2.3.dist-info/WHEEL
jupyxml-0.2.3.dist-info/top_level.txt
jupyxml-0.2.3.dist-info/RECORD
