Metadata-Version: 2.1
Name: jupyxml
Version: 0.2.3
Summary: Show XML files in Jupyter Notebooks easily
Home-page: https://gitlab.com/robertlayton/jupyxml
Author: Robert Layton
Author-email: robertlayton@gmail.com
License: mit
Project-URL: Documentation, https://pyscaffold.org/
Platform: any
Classifier: Development Status :: 4 - Beta
Classifier: Programming Language :: Python
Requires-Dist: lxml
Provides-Extra: development
Requires-Dist: jupyter ; extra == 'development'
Requires-Dist: notebook ; extra == 'development'
Provides-Extra: testing
Requires-Dist: pytest ; extra == 'testing'
Requires-Dist: pytest-cov ; extra == 'testing'
Requires-Dist: hypothesis ; extra == 'testing'
